bnunicode/__init__.py
bnunicode/bnunibtob.py
bnunicode/util/__init__.py
bnunicode/util/common.py
bnunicode/util/decode.py
bnunicode/util/encode.py
bnconverter-0.0.3.dist-info/METADATA
bnconverter-0.0.3.dist-info/WHEEL
bnconverter-0.0.3.dist-info/top_level.txt
bnconverter-0.0.3.dist-info/RECORD
