Metadata-Version: 2.1
Name: bnconverter
Version: 0.0.3
Summary: Python converting Bangla <=> Unicode (UTF-8) for Bengali to Bangla.
Author: Nazrul Islam (Nadeem)
Author-email: <nazrul.devs@gmail.com>
Keywords: python,converting,Unicode,Bengali to Bangla
Classifier: Development Status :: 1 - Planning
Classifier: Intended Audience :: Developers
Classifier: Programming Language :: Python :: 3
Classifier: Operating System :: Unix
Classifier: Operating System :: MacOS :: MacOS X
Classifier: Operating System :: Microsoft :: Windows
Requires-Dist: regex
